openlaw/__init__.py
openlaw-0.1.1.dist-info/WHEEL
openlaw-0.1.1.dist-info/METADATA
openlaw-0.1.1.dist-info/RECORD
