Metadata-Version: 2.1
Name: openlaw
Version: 0.1.1
Summary: A metapackage for OpenLaw Israel projects
License: MIT
Author: Yehuda Deutsch
Author-email: yeh@uda.co.il
Requires-Python: >=3.7,<4.0
Classifier: License :: OSI Approved :: MIT License
Classifier: Programming Language :: Python :: 3
Classifier: Programming Language :: Python :: 3.7
